ikfs_anomaly_detector/__init__.py
ikfs_anomaly_detector/__main__.py
ikfs_anomaly_detector/manual_evaluation.py
ikfs_anomaly_detector/manual_testing.py
ikfs_anomaly_detector/core/__init__.py
ikfs_anomaly_detector/core/config.py
ikfs_anomaly_detector/core/custom_types.py
ikfs_anomaly_detector/core/printer.py
ikfs_anomaly_detector/core/reader.py
ikfs_anomaly_detector/core/tests.py
ikfs_anomaly_detector/core/translation.py
ikfs_anomaly_detector/core/utils.py
ikfs_anomaly_detector/core/format/__init__.py
ikfs_anomaly_detector/core/format/channels.py
ikfs_anomaly_detector/core/format/settings.py
ikfs_anomaly_detector/core/format/states.py
ikfs_anomaly_detector/core/format/telemetry.py
ikfs_anomaly_detector/expert/__init__.py
ikfs_anomaly_detector/expert/analysis.py
ikfs_anomaly_detector/expert/analyzer.py
ikfs_anomaly_detector/expert/rules.py
ikfs_anomaly_detector/expert/testers.py
ikfs_anomaly_detector/expert/tests.py
ikfs_anomaly_detector/intellectual/__init__.py
ikfs_anomaly_detector/intellectual/analysis.py
ikfs_anomaly_detector/intellectual/autoencoder.py
ikfs_anomaly_detector/intellectual/predictor.py
ikfs_anomaly_detector/intellectual/signal_groups.py
ikfs_anomaly_detector/intellectual/tests.py
ikfs_anomaly_detector/intellectual/training.py
ikfs_anomaly_detector/intellectual/utils.py
ikfs_anomaly_detector/models/autoencoder/bfk.h5
ikfs_anomaly_detector/models/autoencoder/bpop.h5
ikfs_anomaly_detector/models/autoencoder/bud.h5
ikfs_anomaly_detector/models/autoencoder/bud_board.h5
ikfs_anomaly_detector/models/autoencoder/fp.h5
ikfs_anomaly_detector/models/autoencoder/mi.h5
ikfs_anomaly_detector/models/autoencoder/mk.h5
ikfs_anomaly_detector/models/autoencoder/ppt.h5
ikfs_anomaly_detector/models/autoencoder/ppt_direction.h5
ikfs_anomaly_detector/models/autoencoder/str.h5
ikfs_anomaly_detector/models/predictor/PptRiple.h5
ikfs_anomaly_detector/models/predictor/PptSampleCount.h5
ikfs_anomaly_detector/models/predictor/ScannerAngle.h5
ikfs_anomaly_detector-1.0.2.dist-info/LICENSE.txt
ikfs_anomaly_detector-1.0.2.dist-info/METADATA
ikfs_anomaly_detector-1.0.2.dist-info/WHEEL
ikfs_anomaly_detector-1.0.2.dist-info/entry_points.txt
ikfs_anomaly_detector-1.0.2.dist-info/top_level.txt
ikfs_anomaly_detector-1.0.2.dist-info/RECORD
