Metadata-Version: 2.1
Name: ikfs-anomaly-detector
Version: 1.0.2
Summary: Программная система обнаружения аномалий в телеметрии бортового фурье-спектрометра ИКФС-2
Home-page: https://github.com/DSPLab-IC6/ikfs_anomaly_detector
Author: Anton Telyshev
Author-email: anton.telishev@yandex.ru
License: MIT
Keywords: ikfs anomaly lstm
Platform: UNKNOWN
Classifier: Development Status :: 3 - Alpha
Classifier: Environment :: MacOS X
Classifier: License :: OSI Approved :: MIT License
Classifier: Natural Language :: Russian
Classifier: Programming Language :: Python :: 3.7
Classifier: Topic :: Scientific/Engineering :: Artificial Intelligence
Requires-Dist: dataclasses
Requires-Dist: h5py
Requires-Dist: keras
Requires-Dist: matplotlib
Requires-Dist: mock
Requires-Dist: numpy
Requires-Dist: pydot
Requires-Dist: tensorflow
